hdfviewer/__init__.py
hdfviewer/__pkginfo__.py
hdfviewer/viewers/MplDataViewer.py
hdfviewer/viewers/MplDataViewer1D.py
hdfviewer/viewers/MplDataViewer2D.py
hdfviewer/viewers/MplDataViewer3D.py
hdfviewer/viewers/__init__.py
hdfviewer/widgets/HDFViewer.py
hdfviewer/widgets/MplOutput.py
hdfviewer/widgets/PathSelector.py
hdfviewer/widgets/__init__.py
hdfviewer-0.11.0.data/scripts/run_hdfviewer
hdfviewer-0.11.0.dist-info/COPYING
hdfviewer-0.11.0.dist-info/LICENSE
hdfviewer-0.11.0.dist-info/METADATA
hdfviewer-0.11.0.dist-info/WHEEL
hdfviewer-0.11.0.dist-info/top_level.txt
hdfviewer-0.11.0.dist-info/RECORD
