Metadata-Version: 2.1
Name: hdfviewer
Version: 0.11.0
Summary: HDF viewer for Jupyter lab notebooks
Home-page: https://code.ill.fr/panosc/data-analysis-services/hdf-data-viewer
Author: Eric Pellegrini
Author-email: pellegrini@ill.fr
Maintainer: Eric Pellegrini
Maintainer-email: pellegrini@ill.fr
License: MIT
Platform: Unix
Platform: Windows
Classifier: Programming Language :: Python :: 3
Classifier: License :: OSI Approved :: MIT License
Classifier: Operating System :: OS Independent
Requires-Dist: numpy
Requires-Dist: matplotlib
Requires-Dist: h5py
Requires-Dist: jupyterlab
Requires-Dist: ipywidgets
Requires-Dist: ipympl
